auth.py
config.py
extractor.py
main.py
sync.py
watcher.py
nia_sync-0.1.3.dist-info/METADATA
nia_sync-0.1.3.dist-info/WHEEL
nia_sync-0.1.3.dist-info/entry_points.txt
nia_sync-0.1.3.dist-info/top_level.txt
nia_sync-0.1.3.dist-info/RECORD
