Metadata-Version: 2.4
Name: nia-sync
Version: 0.1.3
Summary: Keep your local files in sync with Nia Cloud
Requires-Python: >=3.10
Requires-Dist: typer>=0.9.0
Requires-Dist: rich>=13.0.0
Requires-Dist: httpx>=0.25.0
Requires-Dist: watchdog>=4.0.0
